calculator_oluwole_ilesanmi.py
calculator_oluwole_ilesanmi-0.1.0.dist-info/LICENSE
calculator_oluwole_ilesanmi-0.1.0.dist-info/WHEEL
calculator_oluwole_ilesanmi-0.1.0.dist-info/METADATA
calculator_oluwole_ilesanmi-0.1.0.dist-info/RECORD
