Metadata-Version: 2.1
Name: calculator_oluwole_ilesanmi
Version: 0.1.0
Summary: A calculator module.
Author-email: Oluwole Ilesanmi <oluwoleilesanmi@gmail.com>
Requires-Python: >=3.9
Classifier: License :: OSI Approved :: MIT License
